PythonQianyiXuexiShiyongZhinanChuyi/README.md
PythonQianyiXuexiShiyongZhinanChuyi/__init__.py
PythonQianyiXuexiShiyongZhinanChuyi/__main__.py
PythonQianyiXuexiShiyongZhinanChuyi/file.epub
PythonQianyiXuexiShiyongZhinanChuyi/index.html
PythonQianyiXuexiShiyongZhinanChuyi/css/__init__.py
PythonQianyiXuexiShiyongZhinanChuyi/css/annotations.css
PythonQianyiXuexiShiyongZhinanChuyi/css/main.css
PythonQianyiXuexiShiyongZhinanChuyi/css/normalize.css
PythonQianyiXuexiShiyongZhinanChuyi/css/popup.css
PythonQianyiXuexiShiyongZhinanChuyi/font/__init__.py
PythonQianyiXuexiShiyongZhinanChuyi/font/fontello.eot
PythonQianyiXuexiShiyongZhinanChuyi/font/fontello.svg
PythonQianyiXuexiShiyongZhinanChuyi/font/fontello.ttf
PythonQianyiXuexiShiyongZhinanChuyi/font/fontello.woff
PythonQianyiXuexiShiyongZhinanChuyi/img/__init__.py
PythonQianyiXuexiShiyongZhinanChuyi/img/annotator-glyph-sprite.png
PythonQianyiXuexiShiyongZhinanChuyi/img/annotator-icon-sprite.png
PythonQianyiXuexiShiyongZhinanChuyi/img/apple-touch-icon.png
PythonQianyiXuexiShiyongZhinanChuyi/img/cancelfullscreen.png
PythonQianyiXuexiShiyongZhinanChuyi/img/close.png
PythonQianyiXuexiShiyongZhinanChuyi/img/fullscreen.png
PythonQianyiXuexiShiyongZhinanChuyi/img/loader.gif
PythonQianyiXuexiShiyongZhinanChuyi/img/menu-icon.png
PythonQianyiXuexiShiyongZhinanChuyi/img/save.png
PythonQianyiXuexiShiyongZhinanChuyi/img/saved.png
PythonQianyiXuexiShiyongZhinanChuyi/img/settings-s.png
PythonQianyiXuexiShiyongZhinanChuyi/img/settings.png
PythonQianyiXuexiShiyongZhinanChuyi/img/star.png
PythonQianyiXuexiShiyongZhinanChuyi/js/__init__.py
PythonQianyiXuexiShiyongZhinanChuyi/js/epub.js
PythonQianyiXuexiShiyongZhinanChuyi/js/epub.min.js
PythonQianyiXuexiShiyongZhinanChuyi/js/epub.min.map
PythonQianyiXuexiShiyongZhinanChuyi/js/hooks.min.js
PythonQianyiXuexiShiyongZhinanChuyi/js/hooks.min.map
PythonQianyiXuexiShiyongZhinanChuyi/js/reader.js
PythonQianyiXuexiShiyongZhinanChuyi/js/reader.js.map
PythonQianyiXuexiShiyongZhinanChuyi/js/reader.min.js
python_qianyi_xuexi_shiyong_zhinan_chuyi-2024.3.5.0.dist-info/METADATA
python_qianyi_xuexi_shiyong_zhinan_chuyi-2024.3.5.0.dist-info/WHEEL
python_qianyi_xuexi_shiyong_zhinan_chuyi-2024.3.5.0.dist-info/entry_points.txt
python_qianyi_xuexi_shiyong_zhinan_chuyi-2024.3.5.0.dist-info/top_level.txt
python_qianyi_xuexi_shiyong_zhinan_chuyi-2024.3.5.0.dist-info/RECORD
